structify/__init__.py
structify-0.1.0.dist-info/DESCRIPTION.rst
structify-0.1.0.dist-info/METADATA
structify-0.1.0.dist-info/RECORD
structify-0.1.0.dist-info/WHEEL
structify-0.1.0.dist-info/entry_points.txt
structify-0.1.0.dist-info/metadata.json
structify-0.1.0.dist-info/top_level.txt
